Workbook

Sheet Start Here
A1: Excel Portfolio Project — E-commerce Sales & Profitability Dashboard
A3: Goal: turn messy sales records into a clean, decision-ready dashboard that you can explain in an interview.
A5: Phase | B5: Priority | C5: Task | D5: Required output | E5: Skill | F5: Time box | G5: Status | H5: Evidence
A6: 1 | B6: TODAY | C6: Create Cleaned_Data from Raw_Sales; never overwrite Raw_Sales. | D6: One working copy/table | E6: Data discipline | F6: 10 min | G6: Done | H6: Sheet created
A7: 1 | B7: TODAY | C7: Remove exact duplicate orders. | D7: One row per Order_ID | E7: Duplicate handling | F7: 10 min | G7: Done | H7: Row count recorded
A8: 1 | B8: TODAY | C8: Standardize City and Payment_Mode; keep missing City as Unknown. | D8: Consistent labels | E8: Cleaning | F8: 20 min | G8: Done | H8: Before/after values
A9: 1 | B9: TODAY | C9: Use XLOOKUP to add Product_Name, Category, Unit_Price and Unit_Cost. | D9: Four lookup columns | E9: XLOOKUP | F9: 25 min | G9: Done | H9: Formula shown
A10: 1 | B10: TODAY | C10: Flag product codes missing from Product_Lookup; do not invent values. | D10: Data-quality flag | E10: Error handling | F10: 10 min | G10: Done | H10: Exception count
A11: 1 | B11: TODAY | C11: Calculate Gross_Revenue, Discount_Value, Net_Revenue, Cost and Profit. | D11: Five calculated columns | E11: Business formulas | F11: 25 min | G11: Done | H11: Formula checks
A12: 2 | B12: NEXT | C12: Add Profit_Margin, Delivery_Days, Month and Order_Band. | D12: Four analysis columns | E12: IF/date formulas | F12: 30 min | G12: Done | H12: Columns completed
A13: 2 | B13: NEXT | C13: Build PivotTables for month, city, category, channel and salesperson. | D13: Five PivotTables | E13: Pivot analysis | F13: 45 min | G13: Done | H13: Pivot sheet
A14: 2 | B14: NEXT | C14: Create KPIs: Net Revenue, Profit, Margin, Orders and Return Rate. | D14: Five KPI cards | E14: Aggregation | F14: 30 min | G14: Done | H14: Dashboard cards
A15: 3 | B15: NEXT | C15: Create 3–4 useful charts and exclude Grand Totals. | D15: Clean dashboard charts | E15: Chart design | F15: 45 min | G15: Done | H15: Dashboard
A16: 3 | B16: NEXT | C16: Write five findings and three business recommendations. | D16: Insight section | E16: Communication | F16: 30 min | G16: Done | H16: Findings
A17: 3 | B17: FINAL | C17: Quality check, README, screenshot and GitHub upload. | D17: Portfolio package | E17: Documentation/Git | F17: 45 min | G17: Not Started | H17: GitHub link
A20: TODAY'S FINISH LINE: complete tasks 1–6. Do not build the dashboard before the cleaned calculations are checked.
A22: Dataset note: this is a synthetic retail dataset created for learning. Present it as a portfolio project—not employment or client work.

Sheet Cleaned_data
A1: Order_ID | B1: Order_Date | C1: Ship_Date | D1: City | E1: Salesperson | F1: Product_Code | G1: Sales_Channel | H1: Customer_Segment | I1: Quantity | J1: Discount_Pct | K1: Payment_Mode | L1: Returned | M1: Customer_Rating | N1: Product_Name | O1: Category | P1: Unit_Price | Q1: Lookup_Status | R1: Unit_Cost | S1: Gross_Revenue | T1: Discount_Value | U1: Net_Revenue | V1: Cost | W1: Profit | X1: Profit_Margin | Y1: Delivery_Days | Z1: Month | AA1: Order_Band
A2: ORD-5001 | B2: 45792 | C2: 45794 | D2: Delhi | E2: Ananya | F2: P109 | G2: Corporate | H2: Small Business | I2: 2 | J2: 0 | K2: Cash on Delivery | L2: No | M2: 4 | N2: {=_xlfn.XLOOKUP(RawSalesTable5[[#This Row],[Product_Code]],ProductLookupTable[[#All],[Product_Code]],ProductLookupTable[[#All],[Product_Name]],"NOT FOUND")} -> Ergonomic Chair | O2: {=_xlfn.XLOOKUP(RawSalesTable5[[#This Row],[Product_Code]],ProductLookupTable[[#All],[Product_Code]],ProductLookupTable[[#All],[Category]],"NOT FOUND")} -> Furniture | P2: {=_xlfn.XLOOKUP(RawSalesTable5[[#This Row],[Product_Code]],ProductLookupTable[[#All],[Product_Code]],ProductLookupTable[[#All],[Unit_Price]],"NOT FOUND")} -> 10499 | Q2: =IF(COUNTIF(ProductLookupTable[Product_Code],RawSalesTable5[[#This Row],[Product_Code]])=0,"Missing Product","OK") -> OK | R2: {=_xlfn.XLOOKUP(RawSalesTable5[[#This Row],[Product_Code]],ProductLookupTable[[#All],[Product_Code]],ProductLookupTable[[#All],[Unit_Cost]],"NOT FOUND")} -> 7600 | S2: =IFERROR(RawSalesTable5[[#This Row],[Quantity]]*RawSalesTable5[[#This Row],[Unit_Price]],"NOT FOUND") -> 20998 | T2: =IFERROR(RawSalesTable5[[#This Row],[Gross_Revenue]]*RawSalesTable5[[#This Row],[Discount_Pct]],"NOT FOUND") -> 0 | U2: =IFERROR(RawSalesTable5[[#This Row],[Gross_Revenue]]-RawSalesTable5[[#This Row],[Discount_Value]],"NOT FOUND") -> 20998 | V2: =IFERROR(RawSalesTable5[[#This Row],[Quantity]]*RawSalesTable5[[#This Row],[Unit_Cost]],"NOT FOUND") -> 15200 | W2: =IFERROR(RawSalesTable5[[#This Row],[Net_Revenue]]-RawSalesTable5[[#This Row],[Cost]],"NOT FOUND") -> 5798 | X2: =IF(RawSalesTable5[[#This Row],[Lookup_Status]]="Missing Product","",IFERROR(RawSalesTable5[[#This Row],[Profit]]/RawSalesTable5[[#This Row],[Net_Revenue]],0)) -> 0.27612154 | Y2: =RawSalesTable5[[#This Row],[Ship_Date]]-RawSalesTable5[[#This Row],[Order_Date]] -> 2 | Z2: =DATE(YEAR(RawSalesTable5[[#This Row],[Order_Date]]),MONTH(RawSalesTable5[[#This Row],[Order_Date]]),1) -> 45778 | AA2: {=IF(RawSalesTable5[[#This Row],[Lookup_Status]]="Missing Product","",_xlfn.IFS(RawSalesTable5[[#This Row],[Net_Revenue]]>=20000,"High",RawSalesTable5[[#This Row],[Net_Revenue]]>=10000,"Medium",TRUE,"Low"))} -> High
A3: ORD-5002 | B3: 45985 | C3: 45987 | D3: Noida | E3: Rohan | F3: P106 | G3: Website | H3: Small Business | I3: 2 | J3: 0 | K3: Net Banking | L3: No | M3: 3 | N3: {=_xlfn.XLOOKUP(RawSalesTable5[[#This Row],[Product_Code]],ProductLookupTable[[#All],[Product_Code]],ProductLookupTable[[#All],[Product_Name]],"NOT FOUND")} -> Wireless Headset | O3: {=_xlfn.XLOOKUP(RawSalesTable5[[#This Row],[Product_Code]],ProductLookupTable[[#All],[Product_Code]],ProductLookupTable[[#All],[Category]],"NOT FOUND")} -> Audio | P3: {=_xlfn.XLOOKUP(RawSalesTable5[[#This Row],[Product_Code]],ProductLookupTable[[#All],[Product_Code]],ProductLookupTable[[#All],[Unit_Price]],"NOT FOUND")} -> 3499 | Q3: =IF(COUNTIF(ProductLookupTable[Product_Code],RawSalesTable5[[#This Row],[Product_Code]])=0,"Missing Product","OK") -> OK | R3: {=_xlfn.XLOOKUP(RawSalesTable5[[#This Row],[Product_Code]],ProductLookupTable[[#All],[Product_Code]],ProductLookupTable[[#All],[Unit_Cost]],"NOT FOUND")} -> 2100 | S3: =IFERROR(RawSalesTable5[[#This Row],[Quantity]]*RawSalesTable5[[#This Row],[Unit_Price]],"NOT FOUND") -> 6998 | T3: =IFERROR(RawSalesTable5[[#This Row],[Gross_Revenue]]*RawSalesTable5[[#This Row],[Discount_Pct]],"NOT FOUND") -> 0 | U3: =IFERROR(RawSalesTable5[[#This Row],[Gross_Revenue]]-RawSalesTable5[[#This Row],[Discount_Value]],"NOT FOUND") -> 6998 | V3: =IFERROR(RawSalesTable5[[#This Row],[Quantity]]*RawSalesTable5[[#This Row],[Unit_Cost]],"NOT FOUND") -> 4200 | W3: =IFERROR(RawSalesTable5[[#This Row],[Net_Revenue]]-RawSalesTable5[[#This Row],[Cost]],"NOT FOUND") -> 2798 | X3: =IF(RawSalesTable5[[#This Row],[Lookup_Status]]="Missing Product","",IFERROR(RawSalesTable5[[#This Row],[Profit]]/RawSalesTable5[[#This Row],[Net_Revenue]],0)) -> 0.39982852 | Y3: =RawSalesTable5[[#This Row],[Ship_Date]]-RawSalesTable5[[#This Row],[Order_Date]] -> 2 | Z3: =DATE(YEAR(RawSalesTable5[[#This Row],[Order_Date]]),MONTH(RawSalesTable5[[#This Row],[Order_Date]]),1) -> 45962 | AA3: {=IF(RawSalesTable5[[#This Row],[Lookup_Status]]="Missing Product","",_xlfn.IFS(RawSalesTable5[[#This Row],[Net_Revenue]]>=20000,"High",RawSalesTable5[[#This Row],[Net_Revenue]]>=10000,"Medium",TRUE,"Low"))} -> Low
A4: ORD-5003 | B4: 45782 | C4: 45783 | D4: Mathura | E4: Meera | F4: P106 | G4: Website | H4: Corporate | I4: 1 | J4: 0 | K4: Cash on Delivery | L4: No | M4: 3 | N4: {=_xlfn.XLOOKUP(RawSalesTable5[[#This Row],[Product_Code]],ProductLookupTable[[#All],[Product_Code]],ProductLookupTable[[#All],[Product_Name]],"NOT FOUND")} -> Wireless Headset | O4: {=_xlfn.XLOOKUP(RawSalesTable5[[#This Row],[Product_Code]],ProductLookupTable[[#All],[Product_Code]],ProductLookupTable[[#All],[Category]],"NOT FOUND")} -> Audio | P4: {=_xlfn.XLOOKUP(RawSalesTable5[[#This Row],[Product_Code]],ProductLookupTable[[#All],[Product_Code]],ProductLookupTable[[#All],[Unit_Price]],"NOT FOUND")} -> 3499 | Q4: =IF(COUNTIF(ProductLookupTable[Product_Code],RawSalesTable5[[#This Row],[Product_Code]])=0,"Missing Product","OK") -> OK | R4: {=_xlfn.XLOOKUP(RawSalesTable5[[#This Row],[Product_Code]],ProductLookupTable[[#All],[Product_Code]],ProductLookupTable[[#All],[Unit_Cost]],"NOT FOUND")} -> 2100 | S4: =IFERROR(RawSalesTable5[[#This Row],[Quantity]]*RawSalesTable5[[#This Row],[Unit_Price]],"NOT FOUND") -> 3499 | T4: =IFERROR(RawSalesTable5[[#This Row],[Gross_Revenue]]*RawSalesTable5[[#This Row],[Discount_Pct]],"NOT FOUND") -> 0 | U4: =IFERROR(RawSalesTable5[[#This Row],[Gross_Revenue]]-RawSalesTable5[[#This Row],[Discount_Value]],"NOT FOUND") -> 3499 | V4: =IFERROR(RawSalesTable5[[#This Row],[Quantity]]*RawSalesTable5[[#This Row],[Unit_Cost]],"NOT FOUND") -> 2100 | W4: =IFERROR(RawSalesTable5[[#This Row],[Net_Revenue]]-RawSalesTable5[[#This Row],[Cost]],"NOT FOUND") -> 1399 | X4: =IF(RawSalesTable5[[#This Row],[Lookup_Status]]="Missing Product","",IFERROR(RawSalesTable5[[#This Row],[Profit]]/RawSalesTable5[[#This Row],[Net_Revenue]],0)) -> 0.39982852 | Y4: =RawSalesTable5[[#This Row],[Ship_Date]]-RawSalesTable5[[#This Row],[Order_Date]] -> 1 | Z4: =DATE(YEAR(RawSalesTable5[[#This Row],[Order_Date]]),MONTH(RawSalesTable5[[#This Row],[Order_Date]]),1) -> 45778 | AA4: {=IF(RawSalesTable5[[#This Row],[Lookup_Status]]="Missing Product","",_xlfn.IFS(RawSalesTable5[[#This Row],[Net_Revenue]]>=20000,"High",RawSalesTable5[[#This Row],[Net_Revenue]]>=10000,"Medium",TRUE,"Low"))} -> Low
A5: ORD-5004 | B5: 45851 | C5: 45858 | D5: Gurugram | E5: Vikram | F5: P108 | G5: Corporate | H5: Consumer | I5: 2 | J5: 0.05 | K5: Cash on Delivery | L5: No | M5: 4 | N5: {=_xlfn.XLOOKUP(RawSalesTable5[[#This Row],[Product_Code]],ProductLookupTable[[#All],[Product_Code]],ProductLookupTable[[#All],[Product_Name]],"NOT FOUND")} -> SSD 1TB | O5: {=_xlfn.XLOOKUP(RawSalesTable5[[#This Row],[Product_Code]],ProductLookupTable[[#All],[Product_Code]],ProductLookupTable[[#All],[Category]],"NOT FOUND")} -> Storage | P5: {=_xlfn.XLOOKUP(RawSalesTable5[[#This Row],[Product_Code]],ProductLookupTable[[#All],[Product_Code]],ProductLookupTable[[#All],[Unit_Price]],"NOT FOUND")} -> 6999 | Q5: =IF(COUNTIF(ProductLookupTable[Product_Code],RawSalesTable5[[#This Row],[Product_Code]])=0,"Missing Product","OK") -> OK | R5: {=_xlfn.XLOOKUP(RawSalesTable5[[#This Row],[Product_Code]],ProductLookupTable[[#All],[Product_Code]],ProductLookupTable[[#All],[Unit_Cost]],"NOT FOUND")} -> 4900 | S5: =IFERROR(RawSalesTable5[[#This Row],[Quantity]]*RawSalesTable5[[#This Row],[Unit_Price]],"NOT FOUND") -> 13998 | T5: =IFERROR(RawSalesTable5[[#This Row],[Gross_Revenue]]*RawSalesTable5[[#This Row],[Discount_Pct]],"NOT FOUND") -> 699.9 | U5: =IFERROR(RawSalesTable5[[#This Row],[Gross_Revenue]]-RawSalesTable5[[#This Row],[Discount_Value]],"NOT FOUND") -> 13298.1 | V5: =IFERROR(RawSalesTable5[[#This Row],[Quantity]]*RawSalesTable5[[#This Row],[Unit_Cost]],"NOT FOUND") -> 9800 | W5: =IFERROR(RawSalesTable5[[#This Row],[Net_Revenue]]-RawSalesTable5[[#This Row],[Cost]],"NOT FOUND") -> 3498.1 | X5: =IF(RawSalesTable5[[#This Row],[Lookup_Status]]="Missing Product","",IFERROR(RawSalesTable5[[#This Row],[Profit]]/RawSalesTable5[[#This Row],[Net_Revenue]],0)) -> 0.26305262 | Y5: =RawSalesTable5[[#This Row],[Ship_Date]]-RawSalesTable5[[#This Row],[Order_Date]] -> 7 | Z5: =DATE(YEAR(RawSalesTable5[[#This Row],[Order_Date]]),MONTH(RawSalesTable5[[#This Row],[Order_Date]]),1) -> 45839 | AA5: {=IF(RawSalesTable5[[#This Row],[Lookup_Status]]="Missing Product","",_xlfn.IFS(RawSalesTable5[[#This Row],[Net_Revenue]]>=20000,"High",RawSalesTable5[[#This Row],[Net_Revenue]]>=10000,"Medium",TRUE,"Low"))} -> Medium
A6: ORD-5005 | B6: 45838 | C6: 45843 | D6: Faridabad | E6: Sana | F6: P111 | G6: Marketplace | H6: Consumer | I6: 1 | J6: 0.2 | K6: Net Banking | L6: No | M6: 5 | N6: {=_xlfn.XLOOKUP(RawSalesTable5[[#This Row],[Product_Code]],ProductLookupTable[[#All],[Product_Code]],ProductLookupTable[[#All],[Product_Name]],"NOT FOUND")} -> Bluetooth Speaker | O6: {=_xlfn.XLOOKUP(RawSalesTable5[[#This Row],[Product_Code]],ProductLookupTable[[#All],[Product_Code]],ProductLookupTable[[#All],[Category]],"NOT FOUND")} -> Audio | P6: {=_xlfn.XLOOKUP(RawSalesTable5[[#This Row],[Product_Code]],ProductLookupTable[[#All],[Product_Code]],ProductLookupTable[[#All],[Unit_Price]],"NOT FOUND")} -> 2799 | Q6: =IF(COUNTIF(ProductLookupTable[Product_Code],RawSalesTable5[[#This Row],[Product_Code]])=0,"Missing Product","OK") -> OK | R6: {=_xlfn.XLOOKUP(RawSalesTable5[[#This Row],[Product_Code]],ProductLookupTable[[#All],[Product_Code]],ProductLookupTable[[#All],[Unit_Cost]],"NOT FOUND")} -> 1650 | S6: =IFERROR(RawSalesTable5[[#This Row],[Quantity]]*RawSalesTable5[[#This Row],[Unit_Price]],"NOT FOUND") -> 2799 | T6: =IFERROR(RawSalesTable5[[#This Row],[Gross_Revenue]]*RawSalesTable5[[#This Row],[Discount_Pct]],"NOT FOUND") -> 559.8 | U6: =IFERROR(RawSalesTable5[[#This Row],[Gross_Revenue]]-RawSalesTable5[[#This Row],[Discount_Value]],"NOT FOUND") -> 2239.2 | V6: =IFERROR(RawSalesTable5[[#This Row],[Quantity]]*RawSalesTable5[[#This Row],[Unit_Cost]],"NOT FOUND") -> 1650 | W6: =IFERROR(RawSalesTable5[[#This Row],[Net_Revenue]]-RawSalesTable5[[#This Row],[Cost]],"NOT FOUND") -> 589.2 | X6: =IF(RawSalesTable5[[#This Row],[Lookup_Status]]="Missing Product","",IFERROR(RawSalesTable5[[#This Row],[Profit]]/RawSalesTable5[[#This Row],[Net_Revenue]],0)) -> 0.26312969 | Y6: =RawSalesTable5[[#This Row],[Ship_Date]]-RawSalesTable5[[#This Row],[Order_Date]] -> 5 | Z6: =DATE(YEAR(RawSalesTable5[[#This Row],[Order_Date]]),MONTH(RawSalesTable5[[#This Row],[Order_Date]]),1) -> 45809 | AA6: {=IF(RawSalesTable5[[#This Row],[Lookup_Status]]="Missing Product","",_xlfn.IFS(RawSalesTable5[[#This Row],[Net_Revenue]]>=20000,"High",RawSalesTable5[[#This Row],[Net_Revenue]]>=10000,"Medium",TRUE,"Low"))} -> Low
A7: ORD-5006 | B7: 45964 | C7: 45972 | D7: Delhi | E7: Arjun | F7: P106 | G7: Website | H7: Small Business | I7: 4 | J7: 0.1 | K7: Credit Card | L7: No | M7: 4 | N7: {=_xlfn.XLOOKUP(RawSalesTable5[[#This Row],[Product_Code]],ProductLookupTable[[#All],[Product_Code]],ProductLookupTable[[#All],[Product_Name]],"NOT FOUND")} -> Wireless Headset | O7: {=_xlfn.XLOOKUP(RawSalesTable5[[#This Row],[Product_Code]],ProductLookupTable[[#All],[Product_Code]],ProductLookupTable[[#All],[Category]],"NOT FOUND")} -> Audio | P7: {=_xlfn.XLOOKUP(RawSalesTable5[[#This Row],[Product_Code]],ProductLookupTable[[#All],[Product_Code]],ProductLookupTable[[#All],[Unit_Price]],"NOT FOUND")} -> 3499 | Q7: =IF(COUNTIF(ProductLookupTable[Product_Code],RawSalesTable5[[#This Row],[Product_Code]])=0,"Missing Product","OK") -> OK | R7: {=_xlfn.XLOOKUP(RawSalesTable5[[#This Row],[Product_Code]],ProductLookupTable[[#All],[Product_Code]],ProductLookupTable[[#All],[Unit_Cost]],"NOT FOUND")} -> 2100 | S7: =IFERROR(RawSalesTable5[[#This Row],[Quantity]]*RawSalesTable5[[#This Row],[Unit_Price]],"NOT FOUND") -> 13996 | T7: =IFERROR(RawSalesTable5[[#This Row],[Gross_Revenue]]*RawSalesTable5[[#This Row],[Discount_Pct]],"NOT FOUND") -> 1399.6 | U7: =IFERROR(RawSalesTable5[[#This Row],[Gross_Revenue]]-RawSalesTable5[[#This Row],[Discount_Value]],"NOT FOUND") -> 12596.4 | V7: =IFERROR(RawSalesTable5[[#This Row],[Quantity]]*RawSalesTable5[[#This Row],[Unit_Cost]],"NOT FOUND") -> 8400 | W7: =IFERROR(RawSalesTable5[[#This Row],[Net_Revenue]]-RawSalesTable5[[#This Row],[Cost]],"NOT FOUND") -> 4196.4 | X7: =IF(RawSalesTable5[[#This Row],[Lookup_Status]]="Missing Product","",IFERROR(RawSalesTable5[[#This Row],[Profit]]/RawSalesTable5[[#This Row],[Net_Revenue]],0)) -> 0.3331428 | Y7: =RawSalesTable5[[#This Row],[Ship_Date]]-RawSalesTable5[[#This Row],[Order_Date]] -> 8 | Z7: =DATE(YEAR(RawSalesTable5[[#This Row],[Order_Date]]),MONTH(RawSalesTable5[[#This Row],[Order_Date]]),1) -> 45962 | AA7: {=IF(RawSalesTable5[[#This Row],[Lookup_Status]]="Missing Product","",_xlfn.IFS(RawSalesTable5[[#This Row],[Net_Revenue]]>=20000,"High",RawSalesTable5[[#This Row],[Net_Revenue]]>=10000,"Medium",TRUE,"Low"))} -> Medium
A8: ORD-5007 | B8: 45812 | C8: 45816 | D8: Noida | E8: Ananya | F8: P104 | G8: Corporate | H8: Consumer | I8: 5 | J8: 0 | K8: Credit Card | L8: No | M8: 3 | N8: {=_xlfn.XLOOKUP(RawSalesTable5[[#This Row],[Product_Code]],ProductLookupTable[[#All],[Product_Code]],ProductLookupTable[[#All],[Product_Name]],"NOT FOUND")} -> USB-C Hub | O8: {=_xlfn.XLOOKUP(RawSalesTable5[[#This Row],[Product_Code]],ProductLookupTable[[#All],[Product_Code]],ProductLookupTable[[#All],[Category]],"NOT FOUND")} -> Accessories | P8: {=_xlfn.XLOOKUP(RawSalesTable5[[#This Row],[Product_Code]],ProductLookupTable[[#All],[Product_Code]],ProductLookupTable[[#All],[Unit_Price]],"NOT FOUND")} -> 1599 | Q8: =IF(COUNTIF(ProductLookupTable[Product_Code],RawSalesTable5[[#This Row],[Product_Code]])=0,"Missing Product","OK") -> OK | R8: {=_xlfn.XLOOKUP(RawSalesTable5[[#This Row],[Product_Code]],ProductLookupTable[[#All],[Product_Code]],ProductLookupTable[[#All],[Unit_Cost]],"NOT FOUND")} -> 870 | S8: =IFERROR(RawSalesTable5[[#This Row],[Quantity]]*RawSalesTable5[[#This Row],[Unit_Price]],"NOT FOUND") -> 7995 | T8: =IFERROR(RawSalesTable5[[#This Row],[Gross_Revenue]]*RawSalesTable5[[#This Row],[Discount_Pct]],"NOT FOUND") -> 0 | U8: =IFERROR(RawSalesTable5[[#This Row],[Gross_Revenue]]-RawSalesTable5[[#This Row],[Discount_Value]],"NOT FOUND") -> 7995 | V8: =IFERROR(RawSalesTable5[[#This Row],[Quantity]]*RawSalesTable5[[#This Row],[Unit_Cost]],"NOT FOUND") -> 4350 | W8: =IFERROR(RawSalesTable5[[#This Row],[Net_Revenue]]-RawSalesTable5[[#This Row],[Cost]],"NOT FOUND") -> 3645 | X8: =IF(RawSalesTable5[[#This Row],[Lookup_Status]]="Missing Product","",IFERROR(RawSalesTable5[[#This Row],[Profit]]/RawSalesTable5[[#This Row],[Net_Revenue]],0)) -> 0.45590994 | Y8: =RawSalesTable5[[#This Row],[Ship_Date]]-RawSalesTable5[[#This Row],[Order_Date]] -> 4 | Z8: =DATE(YEAR(RawSalesTable5[[#This Row],[Order_Date]]),MONTH(RawSalesTable5[[#This Row],[Order_Date]]),1) -> 45809 | AA8: {=IF(RawSalesTable5[[#This Row],[Lookup_Status]]="Missing Product","",_xlfn.IFS(RawSalesTable5[[#This Row],[Net_Revenue]]>=20000,"High",RawSalesTable5[[#This Row],[Net_Revenue]]>=10000,"Medium",TRUE,"Low"))} -> Low
A9: ORD-5008 | B9: 46020 | C9: 46024 | D9: Mathura | E9: Rohan | F9: P102 | G9: Marketplace | H9: Corporate | I9: 5 | J9: 0 | K9: Debit Card | L9: No | M9: 5 | N9: {=_xlfn.XLOOKUP(RawSalesTable5[[#This Row],[Product_Code]],ProductLookupTable[[#All],[Product_Code]],ProductLookupTable[[#All],[Product_Name]],"NOT FOUND")} -> Mechanical Keyboard | O9: {=_xlfn.XLOOKUP(RawSalesTable5[[#This Row],[Product_Code]],ProductLookupTable[[#All],[Product_Code]],ProductLookupTable[[#All],[Category]],"NOT FOUND")} -> Accessories | P9: {=_xlfn.XLOOKUP(RawSalesTable5[[#This Row],[Product_Code]],ProductLookupTable[[#All],[Product_Code]],ProductLookupTable[[#All],[Unit_Price]],"NOT FOUND")} -> 2499 | Q9: =IF(COUNTIF(ProductLookupTable[Product_Code],RawSalesTable5[[#This Row],[Product_Code]])=0,"Missing Product","OK") -> OK | R9: {=_xlfn.XLOOKUP(RawSalesTable5[[#This Row],[Product_Code]],ProductLookupTable[[#All],[Product_Code]],ProductLookupTable[[#All],[Unit_Cost]],"NOT FOUND")} -> 1450 | S9: =IFERROR(RawSalesTable5[[#This Row],[Quantity]]*RawSalesTable5[[#This Row],[Unit_Price]],"NOT FOUND") -> 12495 | T9: =IFERROR(RawSalesTable5[[#This Row],[Gross_Revenue]]*RawSalesTable5[[#This Row],[Discount_Pct]],"NOT FOUND") -> 0 | U9: =IFERROR(RawSalesTable5[[#This Row],[Gross_Revenue]]-RawSalesTable5[[#This Row],[Discount_Value]],"NOT FOUND") -> 12495 | V9: =IFERROR(RawSalesTable5[[#This Row],[Quantity]]*RawSalesTable5[[#This Row],[Unit_Cost]],"NOT FOUND") -> 7250 | W9: =IFERROR(RawSalesTable5[[#This Row],[Net_Revenue]]-RawSalesTable5[[#This Row],[Cost]],"NOT FOUND") -> 5245 | X9: =IF(RawSalesTable5[[#This Row],[Lookup_Status]]="Missing Product","",IFERROR(RawSalesTable5[[#This Row],[Profit]]/RawSalesTable5[[#This Row],[Net_Revenue]],0)) -> 0.41976791 | Y9: =RawSalesTable5[[#This Row],[Ship_Date]]-RawSalesTable5[[#This Row],[Order_Date]] -> 4 | Z9: =DATE(YEAR(RawSalesTable5[[#This Row],[Order_Date]]),MONTH(RawSalesTable5[[#This Row],[Order_Date]]),1) -> 45992 | AA9: {=IF(RawSalesTable5[[#This Row],[Lookup_Status]]="Missing Product","",_xlfn.IFS(RawSalesTable5[[#This Row],[Net_Revenue]]>=20000,"High",RawSalesTable5[[#This Row],[Net_Revenue]]>=10000,"Medium",TRUE,"Low"))} -> Medium
A10: ORD-5009 | B10: 45829 | C10: 45832 | D10: Gurugram | E10: Meera | F10: P103 | G10: Marketplace | H10: Small Business | I10: 3 | J10: 0.1 | K10: Credit Card | L10: No | M10: 4 | N10: {=_xlfn.XLOOKUP(RawSalesTable5[[#This Row],[Product_Code]],ProductLookupTable[[#All],[Product_Code]],ProductLookupTable[[#All],[Product_Name]],"NOT FOUND")} -> HD Webcam | O10: {=_xlfn.XLOOKUP(RawSalesTable5[[#This Row],[Product_Code]],ProductLookupTable[[#All],[Product_Code]],ProductLookupTable[[#All],[Category]],"NOT FOUND")} -> Accessories | P10: {=_xlfn.XLOOKUP(RawSalesTable5[[#This Row],[Product_Code]],ProductLookupTable[[#All],[Product_Code]],ProductLookupTable[[#All],[Unit_Price]],"NOT FOUND")} -> 2899 | Q10: =IF(COUNTIF(ProductLookupTable[Product_Code],RawSalesTable5[[#This Row],[Product_Code]])=0,"Missing Product","OK") -> OK | R10: {=_xlfn.XLOOKUP(RawSalesTable5[[#This Row],[Product_Code]],ProductLookupTable[[#All],[Product_Code]],ProductLookupTable[[#All],[Unit_Cost]],"NOT FOUND")} -> 1700 | S10: =IFERROR(RawSalesTable5[[#This Row],[Quantity]]*RawSalesTable5[[#This Row],[Unit_Price]],"NOT FOUND") -> 8697 | T10: =IFERROR(RawSalesTable5[[#This Row],[Gross_Revenue]]*RawSalesTable5[[#This Row],[Discount_Pct]],"NOT FOUND") -> 869.7 | U10: =IFERROR(RawSalesTable5[[#This Row],[Gross_Revenue]]-RawSalesTable5[[#This Row],[Discount_Value]],"NOT FOUND") -> 7827.3 | V10: =IFERROR(RawSalesTable5[[#This Row],[Quantity]]*RawSalesTable5[[#This Row],[Unit_Cost]],"NOT FOUND") -> 5100 | W10: =IFERROR(RawSalesTable5[[#This Row],[Net_Revenue]]-RawSalesTable5[[#This Row],[Cost]],"NOT FOUND") -> 2727.3 | X10: =IF(RawSalesTable5[[#This Row],[Lookup_Status]]="Missing Product","",IFERROR(RawSalesTable5[[#This Row],[Profit]]/RawSalesTable5[[#This Row],[Net_Revenue]],0)) -> 0.34843433 | Y10: =RawSalesTable5[[#This Row],[Ship_Date]]-RawSalesTable5[[#This Row],[Order_Date]] -> 3 | Z10: =DATE(YEAR(RawSalesTable5[[#This Row],[Order_Date]]),MONTH(RawSalesTable5[[#This Row],[Order_Date]]),1) -> 45809 | AA10: {=IF(RawSalesTable5[[#This Row],[Lookup_Status]]="Missing Product","",_xlfn.IFS(RawSalesTable5[[#This Row],[Net_Revenue]]>=20000,"High",RawSalesTable5[[#This Row],[Net_Revenue]]>=10000,"Medium",TRUE,"Low"))} -> Low
A11: ORD-5010 | B11: 45778 | C11: 45786 | D11: Faridabad | E11: Vikram | F11: P101 | G11: Retail Store | H11: Small Business | I11: 3 | J11: 0.2 | K11: Credit Card | L11: Yes | M11: 1 | N11: {=_xlfn.XLOOKUP(RawSalesTable5[[#This Row],[Product_Code]],ProductLookupTable[[#All],[Product_Code]],ProductLookupTable[[#All],[Product_Name]],"NOT FOUND")} -> Wireless Mouse | O11: {=_xlfn.XLOOKUP(RawSalesTable5[[#This Row],[Product_Code]],ProductLookupTable[[#All],[Product_Code]],ProductLookupTable[[#All],[Category]],"NOT FOUND")} -> Accessories | P11: {=_xlfn.XLOOKUP(RawSalesTable5[[#This Row],[Product_Code]],ProductLookupTable[[#All],[Product_Code]],ProductLookupTable[[#All],[Unit_Price]],"NOT FOUND")} -> 799 | Q11: =IF(COUNTIF(ProductLookupTable[Product_Code],RawSalesTable5[[#This Row],[Product_Code]])=0,"Missing Product","OK") -> OK | R11: {=_xlfn.XLOOKUP(RawSalesTable5[[#This Row],[Product_Code]],ProductLookupTable[[#All],[Product_Code]],ProductLookupTable[[#All],[Unit_Cost]],"NOT FOUND")} -> 420 | S11: =IFERROR(RawSalesTable5[[#This Row],[Quantity]]*RawSalesTable5[[#This Row],[Unit_Price]],"NOT FOUND") -> 2397 | T11: =IFERROR(RawSalesTable5[[#This Row],[Gross_Revenue]]*RawSalesTable5[[#This Row],[Discount_Pct]],"NOT FOUND") -> 479.4 | U11: =IFERROR(RawSalesTable5[[#This Row],[Gross_Revenue]]-RawSalesTable5[[#This Row],[Discount_Value]],"NOT FOUND") -> 1917.6 | V11: =IFERROR(RawSalesTable5[[#This Row],[Quantity]]*RawSalesTable5[[#This Row],[Unit_Cost]],"NOT FOUND") -> 1260 | W11: =IFERROR(RawSalesTable5[[#This Row],[Net_Revenue]]-RawSalesTable5[[#This Row],[Cost]],"NOT FOUND") -> 657.6 | X11: =IF(RawSalesTable5[[#This Row],[Lookup_Status]]="Missing Product","",IFERROR(RawSalesTable5[[#This Row],[Profit]]/RawSalesTable5[[#This Row],[Net_Revenue]],0)) -> 0.34292866 | Y11: =RawSalesTable5[[#This Row],[Ship_Date]]-RawSalesTable5[[#This Row],[Order_Date]] -> 8 | Z11: =DATE(YEAR(RawSalesTable5[[#This Row],[Order_Date]]),MONTH(RawSalesTable5[[#This Row],[Order_Date]]),1) -> 45778 | AA11: {=IF(RawSalesTable5[[#This Row],[Lookup_Status]]="Missing Product","",_xlfn.IFS(RawSalesTable5[[#This Row],[Net_Revenue]]>=20000,"High",RawSalesTable5[[#This Row],[Net_Revenue]]>=10000,"Medium",TRUE,"Low"))} -> Low
A12: ORD-5011 | B12: 45695 | C12: 45699 | D12: Delhi | E12: Sana | F12: P104 | G12: Website | H12: Small Business | I12: 2 | J12: 0.1 | K12: Credit Card | L12: No | M12: 5 | N12: {=_xlfn.XLOOKUP(RawSalesTable5[[#This Row],[Product_Code]],ProductLookupTable[[#All],[Product_Code]],ProductLookupTable[[#All],[Product_Name]],"NOT FOUND")} -> USB-C Hub | O12: {=_xlfn.XLOOKUP(RawSalesTable5[[#This Row],[Product_Code]],ProductLookupTable[[#All],[Product_Code]],ProductLookupTable[[#All],[Category]],"NOT FOUND")} -> Accessories | P12: {=_xlfn.XLOOKUP(RawSalesTable5[[#This Row],[Product_Code]],ProductLookupTable[[#All],[Product_Code]],ProductLookupTable[[#All],[Unit_Price]],"NOT FOUND")} -> 1599 | Q12: =IF(COUNTIF(ProductLookupTable[Product_Code],RawSalesTable5[[#This Row],[Product_Code]])=0,"Missing Product","OK") -> OK | R12: {=_xlfn.XLOOKUP(RawSalesTable5[[#This Row],[Product_Code]],ProductLookupTable[[#All],[Product_Code]],ProductLookupTable[[#All],[Unit_Cost]],"NOT FOUND")} -> 870 | S12: =IFERROR(RawSalesTable5[[#This Row],[Quantity]]*RawSalesTable5[[#This Row],[Unit_Price]],"NOT FOUND") -> 3198 | T12: =IFERROR(RawSalesTable5[[#This Row],[Gross_Revenue]]*RawSalesTable5[[#This Row],[Discount_Pct]],"NOT FOUND") -> 319.8 | U12: =IFERROR(RawSalesTable5[[#This Row],[Gross_Revenue]]-RawSalesTable5[[#This Row],[Discount_Value]],"NOT FOUND") -> 2878.2 | V12: =IFERROR(RawSalesTable5[[#This Row],[Quantity]]*RawSalesTable5[[#This Row],[Unit_Cost]],"NOT FOUND") -> 1740 | W12: =IFERROR(RawSalesTable5[[#This Row],[Net_Revenue]]-RawSalesTable5[[#This Row],[Cost]],"NOT FOUND") -> 1138.2 | X12: =IF(RawSalesTable5[[#This Row],[Lookup_Status]]="Missing Product","",IFERROR(RawSalesTable5[[#This Row],[Profit]]/RawSalesTable5[[#This Row],[Net_Revenue]],0)) -> 0.39545549 | Y12: =RawSalesTable5[[#This Row],[Ship_Date]]-RawSalesTable5[[#This Row],[Order_Date]] -> 4 | Z12: =DATE(YEAR(RawSalesTable5[[#This Row],[Order_Date]]),MONTH(RawSalesTable5[[#This Row],[Order_Date]]),1) -> 45689 | AA12: {=IF(RawSalesTable5[[#This Row],[Lookup_Status]]="Missing Product","",_xlfn.IFS(RawSalesTable5[[#This Row],[Net_Revenue]]>=20000,"High",RawSalesTable5[[#This Row],[Net_Revenue]]>=10000,"Medium",TRUE,"Low"))} -> Low
A13: ORD-5012 | B13: 46006 | C13: 46014 | D13: Noida | E13: Arjun | F13: P102 | G13: Corporate | H13: Consumer | I13: 5 | J13: 0.1 | K13: Cash on Delivery | L13: No | M13: 5 | N13: {=_xlfn.XLOOKUP(RawSalesTable5[[#This Row],[Product_Code]],ProductLookupTable[[#All],[Product_Code]],ProductLookupTable[[#All],[Product_Name]],"NOT FOUND")} -> Mechanical Keyboard | O13: {=_xlfn.XLOOKUP(RawSalesTable5[[#This Row],[Product_Code]],ProductLookupTable[[#All],[Product_Code]],ProductLookupTable[[#All],[Category]],"NOT FOUND")} -> Accessories | P13: {=_xlfn.XLOOKUP(RawSalesTable5[[#This Row],[Product_Code]],ProductLookupTable[[#All],[Product_Code]],ProductLookupTable[[#All],[Unit_Price]],"NOT FOUND")} -> 2499 | Q13: =IF(COUNTIF(ProductLookupTable[Product_Code],RawSalesTable5[[#This Row],[Product_Code]])=0,"Missing Product","OK") -> OK | R13: {=_xlfn.XLOOKUP(RawSalesTable5[[#This Row],[Product_Code]],ProductLookupTable[[#All],[Product_Code]],ProductLookupTable[[#All],[Unit_Cost]],"NOT FOUND")} -> 1450 | S13: =IFERROR(RawSalesTable5[[#This Row],[Quantity]]*RawSalesTable5[[#This Row],[Unit_Price]],"NOT FOUND") -> 12495 | T13: =IFERROR(RawSalesTable5[[#This Row],[Gross_Revenue]]*RawSalesTable5[[#This Row],[Discount_Pct]],"NOT FOUND") -> 1249.5 | U13: =IFERROR(RawSalesTable5[[#This Row],[Gross_Revenue]]-RawSalesTable5[[#This Row],[Discount_Value]],"NOT FOUND") -> 11245.5 | V13: =IFERROR(RawSalesTable5[[#This Row],[Quantity]]*RawSalesTable5[[#This Row],[Unit_Cost]],"NOT FOUND") -> 7250 | W13: =IFERROR(RawSalesTable5[[#This Row],[Net_Revenue]]-RawSalesTable5[[#This Row],[Cost]],"NOT FOUND") -> 3995.5 | X13: =IF(RawSalesTable5[[#This Row],[Lookup_Status]]="Missing Product","",IFERROR(RawSalesTable5[[#This Row],[Profit]]/RawSalesTable5[[#This Row],[Net_Revenue]],0)) -> 0.35529767 | Y13: =RawSalesTable5[[#This Row],[Ship_Date]]-RawSalesTable5[[#This Row],[Order_Date]] -> 8 | Z13: =DATE(YEAR(RawSalesTable5[[#This Row],[Order_Date]]),MONTH(RawSalesTable5[[#This Row],[Order_Date]]),1) -> 45992 | AA13: {=IF(RawSalesTable5[[#This Row],[Lookup_Status]]="Missing Product","",_xlfn.IFS(RawSalesTable5[[#This Row],[Net_Revenue]]>=20000,"High",RawSalesTable5[[#This Row],[Net_Revenue]]>=10000,"Medium",TRUE,"Low"))} -> Medium
... A361: ORD-5360 | B361: 45877 | C361: 45880 | D361: Faridabad | E361: Arjun | F361: P108 | G361: Retail Store | H361: Corporate | I361: 3 | J361: 0.15 | K361: UPI | L361: No | M361: 3 | N361: {=_xlfn.XLOOKUP(RawSalesTable5[[#This Row],[Product_Code]],ProductLookupTable[[#All],[Product_Code]],ProductLookupTable[[#All],[Product_Name]],"NOT FOUND")} -> SSD 1TB | O361: {=_xlfn.XLOOKUP(RawSalesTable5[[#This Row],[Product_Code]],ProductLookupTable[[#All],[Product_Code]],ProductLookupTable[[#All],[Category]],"NOT FOUND")} -> Storage | P361: {=_xlfn.XLOOKUP(RawSalesTable5[[#This Row],[Product_Code]],ProductLookupTable[[#All],[Product_Code]],ProductLookupTable[[#All],[Unit_Price]],"NOT FOUND")} -> 6999 | Q361: =IF(COUNTIF(ProductLookupTable[Product_Code],RawSalesTable5[[#This Row],[Product_Code]])=0,"Missing Product","OK") -> OK | R361: {=_xlfn.XLOOKUP(RawSalesTable5[[#This Row],[Product_Code]],ProductLookupTable[[#All],[Product_Code]],ProductLookupTable[[#All],[Unit_Cost]],"NOT FOUND")} -> 4900 | S361: =IFERROR(RawSalesTable5[[#This Row],[Quantity]]*RawSalesTable5[[#This Row],[Unit_Price]],"NOT FOUND") -> 20997 | T361: =IFERROR(RawSalesTable5[[#This Row],[Gross_Revenue]]*RawSalesTable5[[#This Row],[Discount_Pct]],"NOT FOUND") -> 3149.55 | U361: =IFERROR(RawSalesTable5[[#This Row],[Gross_Revenue]]-RawSalesTable5[[#This Row],[Discount_Value]],"NOT FOUND") -> 17847.45 | V361: =IFERROR(RawSalesTable5[[#This Row],[Quantity]]*RawSalesTable5[[#This Row],[Unit_Cost]],"NOT FOUND") -> 14700 | W361: =IFERROR(RawSalesTable5[[#This Row],[Net_Revenue]]-RawSalesTable5[[#This Row],[Cost]],"NOT FOUND") -> 3147.45 | X361: =IF(RawSalesTable5[[#This Row],[Lookup_Status]]="Missing Product","",IFERROR(RawSalesTable5[[#This Row],[Profit]]/RawSalesTable5[[#This Row],[Net_Revenue]],0)) -> 0.17635292 | Y361: =RawSalesTable5[[#This Row],[Ship_Date]]-RawSalesTable5[[#This Row],[Order_Date]] -> 3 | Z361: =DATE(YEAR(RawSalesTable5[[#This Row],[Order_Date]]),MONTH(RawSalesTable5[[#This Row],[Order_Date]]),1) -> 45870 | AA361: {=IF(RawSalesTable5[[#This Row],[Lookup_Status]]="Missing Product","",_xlfn.IFS(RawSalesTable5[[#This Row],[Net_Revenue]]>=20000,"High",RawSalesTable5[[#This Row],[Net_Revenue]]>=10000,"Medium",TRUE,"Low"))} -> Medium

Sheet Raw_Sales
A1: Order_ID | B1: Order_Date | C1: Ship_Date | D1: City | E1: Salesperson | F1: Product_Code | G1: Sales_Channel | H1: Customer_Segment | I1: Quantity | J1: Discount_Pct | K1: Payment_Mode | L1: Returned | M1: Customer_Rating
A2: ORD-5001 | B2: 45792 | C2: 45794 | D2: Delhi | E2: Ananya | F2: P109 | G2: Corporate | H2: Small Business | I2: 2 | J2: 0 | K2: Cash on Delivery | L2: No | M2: 4
A3: ORD-5002 | B3: 45985 | C3: 45987 | D3: NOIDA | E3: Rohan | F3: P106 | G3: Website | H3: Small Business | I3: 2 | J3: 0 | K3: Net Banking | L3: No | M3: 3
A4: ORD-5003 | B4: 45782 | C4: 45783 | D4: MATHURA | E4: Meera | F4: P106 | G4: Website | H4: Corporate | I4: 1 | J4: 0 | K4: Cash on Delivery | L4: No | M4: 3
A5: ORD-5004 | B5: 45851 | C5: 45858 | D5: Gurgaon | E5: Vikram | F5: P108 | G5: Corporate | H5: Consumer | I5: 2 | J5: 0.05 | K5: Cash on Delivery | L5: No | M5: 4
A6: ORD-5005 | B6: 45838 | C6: 45843 | D6: faridabad | E6: Sana | F6: P111 | G6: Marketplace | H6: Consumer | I6: 1 | J6: 0.2 | K6: Net Banking | L6: No | M6: 5
A7: ORD-5006 | B7: 45964 | C7: 45972 | D7: delhi | E7: Arjun | F7: P106 | G7: Website | H7: Small Business | I7: 4 | J7: 0.1 | K7: Credit Card | L7: No | M7: 4
A8: ORD-5007 | B8: 45812 | C8: 45816 | D8: Noida | E8: Ananya | F8: P104 | G8: Corporate | H8: Consumer | I8: 5 | J8: 0 | K8: credit card | L8: No | M8: 3
A9: ORD-5008 | B9: 46020 | C9: 46024 | D9: MATHURA | E9: Rohan | F9: P102 | G9: Marketplace | H9: Corporate | I9: 5 | J9: 0 | K9: Debit Card | L9: No | M9: 5
A10: ORD-5009 | B10: 45829 | C10: 45832 | D10: Gurgaon | E10: Meera | F10: P103 | G10: Marketplace | H10: Small Business | I10: 3 | J10: 0.1 | K10: credit card | L10: No | M10: 4
A11: ORD-5010 | B11: 45778 | C11: 45786 | D11: Faridabad | E11: Vikram | F11: P101 | G11: Retail Store | H11: Small Business | I11: 3 | J11: 0.2 | K11: Credit Card | L11: Yes | M11: 1
A12: ORD-5011 | B12: 45695 | C12: 45699 | D12: New Delhi | E12: Sana | F12: P104 | G12: Website | H12: Small Business | I12: 2 | J12: 0.1 | K12: Credit Card | L12: No | M12: 5
A13: ORD-5012 | B13: 46006 | C13: 46014 | D13: noida | E13: Arjun | F13: P102 | G13: Corporate | H13: Consumer | I13: 5 | J13: 0.1 | K13: Cash on Delivery | L13: No | M13: 5
... A20: ORD-5019 | B20: 45959 | C20: 45964 | D20: Gurgaon | E20: Ananya | F20: P105 | G20: Website | H20: Small Business | I20: 2 | J20: 0 | K20: upi | L20: No | M20: 3
A21: ORD-5020 | B21: 46013 | C21: 46014 | E21: Rohan | F21: P104 | G21: Retail Store | H21: Corporate | I21: 2 | J21: 0.15 | K21: Credit Card | L21: Yes | M21: 1
A22: ORD-5021 | B22: 45714 | C22: 45720 | D22: DELHI | E22: Meera | F22: P110 | G22: Marketplace | H22: Consumer | I22: 1 | J22: 0.1 | K22: credit card | L22: No | M22: 4
A23: ORD-5022 | B23: 45783 | C23: 45784 | D23: NOIDA | E23: Vikram | F23: P112 | G23: Corporate | H23: Corporate | I23: 5 | J23: 0.1 | K23: credit card | L23: No | M23: 3
A24: ORD-5023 | B24: 45851 | C24: 45855 | D24: MATHURA | E24: Sana | F24: P102 | G24: Corporate | H24: Small Business | I24: 2 | J24: 0 | K24: Debit Card | L24: No | M24: 5
A25: ORD-5024 | B25: 45828 | C25: 45831 | D25: GURUGRAM | E25: Arjun | F25: P104 | G25: Corporate | H25: Corporate | I25: 1 | J25: 0 | K25: Net Banking | L25: No | M25: 5
A26: ORD-5025 | B26: 45702 | C26: 45710 | D26: faridabad | E26: Ananya | F26: P110 | G26: Website | H26: Corporate | I26: 1 | J26: 0.15 | K26: COD | L26: No | M26: 4
A27: ORD-5026 | B27: 45802 | C27: 45808 | D27: Delhi | E27: Rohan | F27: P107 | G27: Corporate | H27: Small Business | I27: 4 | J27: 0.2 | K27: Debit Card | L27: No | M27: 5
A28: ORD-5027 | B28: 46010 | C28: 46012 | D28: Noida | E28: Meera | F28: P102 | G28: Corporate | H28: Small Business | I28: 4 | J28: 0.15 | K28: UPI | L28: No | M28: 3
A29: ORD-5028 | B29: 45947 | C29: 45952 | D29: Mathura | E29: Vikram | F29: P112 | G29: Website | H29: Consumer | I29: 1 | J29: 0 | K29: upi | L29: No | M29: 5
A30: ORD-5029 | B30: 45845 | C30: 45849 | D30: Gurgaon | E30: Sana | F30: P106 | G30: Retail Store | H30: Corporate | I30: 2 | J30: 0.2 | K30: Debit Card | L30: No | M30: 4
A31: ORD-5030 | B31: 45754 | C31: 45761 | D31: faridabad | E31: Arjun | F31: P112 | G31: Corporate | H31: Consumer | I31: 5 | J31: 0 | K31: COD | L31: No | M31: 5
A32: ORD-5031 | B32: 45974 | C32: 45982 | D32: DELHI | E32: Ananya | F32: P102 | G32: Marketplace | H32: Consumer | I32: 4 | J32: 0.2 | K32: COD | L32: No | M32: 4
A33: ORD-5032 | B33: 45899 | C33: 45905 | D33: noida | E33: Rohan | F33: P112 | G33: Marketplace | H33: Small Business | I33: 5 | J33: 0 | K33: COD | L33: No | M33: 5
... A75: ORD-5074 | B75: 45848 | C75: 45850 | D75: gurugram | E75: Rohan | F75: P101 | G75: Website | H75: Consumer | I75: 5 | J75: 0.1 | K75: upi | L75: No | M75: 4
A76: ORD-5075 | B76: 45721 | C76: 45728 | E76: Meera | F76: P109 | G76: Retail Store | H76: Consumer | I76: 4 | J76: 0.1 | K76: COD | L76: Yes | M76: 1
A77: ORD-5076 | B77: 45969 | C77: 45974 | D77: Delhi | E77: Vikram | F77: P105 | G77: Retail Store | H77: Small Business | I77: 4 | J77: 0 | K77: upi | L77: No | M77: 5
A78: ORD-5077 | B78: 45930 | C78: 45932 | D78: Noida | E78: Sana | F78: P112 | G78: Marketplace | H78: Corporate | I78: 1 | J78: 0.1 | K78: Net Banking | L78: No | M78: 5
A79: ORD-5078 | B79: 45766 | C79: 45773 | D79: MATHURA | E79: Arjun | F79: P104 | G79: Retail Store | H79: Consumer | I79: 3 | J79: 0.1 | K79: Net Banking | L79: No | M79: 3
A80: ORD-5079 | B80: 45791 | C80: 45795 | D80: Gurugram | E80: Ananya | F80: P111 | G80: Corporate | H80: Corporate | I80: 1 | J80: 0.1 | K80: Net Banking | L80: Yes | M80: 1
A81: ORD-5080 | B81: 45814 | C81: 45816 | D81: faridabad | E81: Rohan | F81: P106 | G81: Corporate | H81: Corporate | I81: 5 | J81: 0.05 | K81: Credit Card | L81: No | M81: 3
A82: ORD-5081 | B82: 45760 | C82: 45762 | D82: New Delhi | E82: Meera | F82: P103 | G82: Retail Store | H82: Small Business | I82: 5 | J82: 0 | K82: Cash on Delivery | L82: No | M82: 3
A83: ORD-5082 | B83: 45798 | C83: 45801 | D83: Noida | E83: Vikram | F83: P109 | G83: Marketplace | H83: Consumer | I83: 3 | J83: 0 | K83: upi | L83: No | M83: 4
A84: ORD-5083 | B84: 45689 | C84: 45696 | D84: Mathura | E84: Sana | F84: P101 | G84: Corporate | H84: Small Business | I84: 5 | J84: 0.15 | K84: Net Banking | L84: No | M84: 4
A85: ORD-5084 | B85: 45925 | C85: 45932 | D85: GURUGRAM | E85: Arjun | F85: P103 | G85: Website | H85: Consumer | I85: 4 | J85: 0 | K85: COD | L85: No | M85: 4
A86: ORD-5085 | B86: 45967 | C86: 45975 | D86: FARIDABAD | E86: Ananya | F86: P105 | G86: Retail Store | H86: Consumer | I86: 2 | J86: 0 | K86: UPI | L86: No | M86: 4
A87: ORD-5086 | B87: 45772 | C87: 45777 | D87: Delhi | E87: Rohan | F87: P107 | G87: Marketplace | H87: Consumer | I87: 2 | J87: 0.1 | K87: Debit Card | L87: No | M87: 5
A88: ORD-5087 | B88: 45939 | C88: 45941 | D88: Noida | E88: Meera | F88: P109 | G88: Marketplace | H88: Corporate | I88: 2 | J88: 0.15 | K88: UPI | L88: No | M88: 4
... A122: ORD-5121 | B122: 45802 | C122: 45809 | D122: Delhi | E122: Ananya | F122: P102 | G122: Retail Store | H122: Corporate | I122: 5 | J122: 0.1 | K122: Net Banking | L122: No | M122: 3
A123: ORD-5122 | B123: 45969 | C123: 45977 | E123: Rohan | F123: P110 | G123: Website | H123: Small Business | I123: 4 | J123: 0 | K123: upi | L123: No | M123: 5
A124: ORD-5123 | B124: 45730 | C124: 45737 | D124: mathura | E124: Meera | F124: P101 | G124: Retail Store | H124: Small Business | I124: 5 | J124: 0.1 | K124: COD | L124: Yes | M124: 3
A125: ORD-5124 | B125: 45744 | C125: 45750 | D125: Gurugram | E125: Vikram | F125: P101 | G125: Website | H125: Small Business | I125: 5 | J125: 0.1 | K125: upi | L125: No | M125: 3
A126: ORD-5125 | B126: 45932 | C126: 45934 | D126: Faridabad | E126: Sana | F126: P108 | G126: Retail Store | H126: Corporate | I126: 3 | J126: 0 | K126: credit card | L126: No | M126: 5
A127: ORD-5126 | B127: 45774 | C127: 45782 | D127: Delhi | E127: Arjun | F127: P112 | G127: Website | H127: Small Business | I127: 2 | J127: 0.2 | K127: credit card | L127: No | M127: 5
A128: ORD-5127 | B128: 45959 | C128: 45965 | D128: noida | E128: Ananya | F128: P109 | G128: Marketplace | H128: Small Business | I128: 5 | J128: 0.15 | K128: Cash on Delivery | L128: No | M128: 4
A129: ORD-5128 | B129: 45974 | C129: 45981 | D129: mathura | E129: Rohan | F129: P109 | G129: Website | H129: Consumer | I129: 3 | J129: 0 | K129: upi | L129: Yes | M129: 2
A130: ORD-5129 | B130: 45748 | C130: 45750 | D130: gurugram | E130: Meera | F130: P109 | G130: Retail Store | H130: Consumer | I130: 1 | J130: 0 | K130: credit card | L130: No | M130: 4
A131: ORD-5130 | B131: 45907 | C131: 45911 | D131: Faridabad | E131: Vikram | F131: P103 | G131: Marketplace | H131: Consumer | I131: 3 | J131: 0.1 | K131: upi | L131: No | M131: 4
A132: ORD-5131 | B132: 45956 | C132: 45958 | D132: New Delhi | E132: Sana | F132: P111 | G132: Corporate | H132: Small Business | I132: 5 | J132: 0.2 | K132: Cash on Delivery | L132: No | M132: 5
A133: ORD-5132 | B133: 45707 | C133: 45713 | D133: Noida | E133: Arjun | F133: P112 | G133: Corporate | H133: Small Business | I133: 5 | J133: 0.1 | K133: Net Banking | L133: Yes | M133: 2
A134: ORD-5133 | B134: 45918 | C134: 45924 | D134: Mathura | E134: Ananya | F134: P109 | G134: Corporate | H134: Small Business | I134: 1 | J134: 0.1 | K134: credit card | L134: No | M134: 3
A135: ORD-5134 | B135: 45791 | C135: 45799 | D135: Gurugram | E135: Rohan | F135: P101 | G135: Retail Store | H135: Consumer | I135: 2 | J135: 0.05 | K135: credit card | L135: No | M135: 3
... A189: ORD-5188 | B189: 45683 | C189: 45688 | D189: Mathura | E189: Rohan | F189: P101 | G189: Retail Store | H189: Consumer | I189: 2 | J189: 0.2 | K189: Credit Card | L189: No | M189: 4
A190: ORD-5189 | B190: 45895 | C190: 45902 | E190: Meera | F190: P112 | G190: Marketplace | H190: Consumer | I190: 2 | J190: 0.1 | K190: UPI | L190: No | M190: 4
A191: ORD-5190 | B191: 45694 | C191: 45696 | D191: Faridabad | E191: Vikram | F191: P103 | G191: Retail Store | H191: Corporate | I191: 2 | J191: 0 | K191: Credit Card | L191: No | M191: 3
A192: ORD-5191 | B192: 45733 | C192: 45736 | D192: New Delhi | E192: Sana | F192: P107 | G192: Corporate | H192: Consumer | I192: 2 | J192: 0 | K192: UPI | L192: No | M192: 3
A193: ORD-5192 | B193: 45733 | C193: 45736 | D193: NOIDA | E193: Arjun | F193: P106 | G193: Retail Store | H193: Consumer | I193: 4 | J193: 0.2 | K193: Debit Card | L193: Yes | M193: 2
A194: ORD-5193 | B194: 45957 | C194: 45965 | D194: mathura | E194: Ananya | F194: P104 | G194: Retail Store | H194: Consumer | I194: 3 | J194: 0.15 | K194: UPI | L194: No | M194: 4
A195: ORD-5194 | B195: 45914 | C195: 45915 | D195: gurugram | E195: Rohan | F195: P110 | G195: Website | H195: Corporate | I195: 4 | J195: 0 | K195: upi | L195: No | M195: 5
A196: ORD-5195 | B196: 45697 | C196: 45702 | D196: Faridabad | E196: Meera | F196: P111 | G196: Corporate | H196: Corporate | I196: 2 | J196: 0 | K196: UPI | L196: No | M196: 4
A197: ORD-5196 | B197: 45999 | C197: 46007 | D197: Delhi | E197: Vikram | F197: P112 | G197: Retail Store | H197: Corporate | I197: 1 | J197: 0.2 | K197: UPI | L197: No | M197: 3
A198: ORD-5197 | B198: 45692 | C198: 45700 | D198: NOIDA | E198: Sana | F198: P106 | G198: Marketplace | H198: Consumer | I198: 3 | J198: 0 | K198: UPI | L198: No | M198: 5
A199: ORD-5198 | B199: 45958 | C199: 45964 | D199: MATHURA | E199: Arjun | F199: P101 | G199: Corporate | H199: Small Business | I199: 3 | J199: 0.15 | K199: Credit Card | L199: Yes | M199: 1
A200: ORD-5199 | B200: 45794 | C200: 45799 | D200: Gurugram | E200: Ananya | F200: P108 | G200: Marketplace | H200: Small Business | I200: 2 | J200: 0.1 | K200: credit card | L200: No | M200: 5
A201: ORD-5200 | B201: 45750 | C201: 45758 | D201: Faridabad | E201: Rohan | F201: P105 | G201: Corporate | H201: Consumer | I201: 1 | J201: 0 | K201: Cash on Delivery | L201: No | M201: 3
A202: ORD-5201 | B202: 45752 | C202: 45757 | D202: Delhi | E202: Meera | F202: P105 | G202: Marketplace | H202: Consumer | I202: 2 | J202: 0 | K202: Cash on Delivery | L202: No | M202: 4
... A242: ORD-5241 | B242: 45729 | C242: 45732 | D242: DELHI | E242: Ananya | F242: P105 | G242: Corporate | H242: Corporate | I242: 5 | J242: 0.1 | K242: upi | L242: No | M242: 3
A243: ORD-5242 | B243: 45778 | C243: 45784 | E243: Rohan | F243: P110 | G243: Retail Store | H243: Small Business | I243: 3 | J243: 0 | K243: upi | L243: No | M243: 5
A244: ORD-5243 | B244: 45805 | C244: 45813 | D244: mathura | E244: Meera | F244: P111 | G244: Marketplace | H244: Consumer | I244: 1 | J244: 0 | K244: Net Banking | L244: No | M244: 5
A245: ORD-5244 | B245: 45900 | C245: 45903 | D245: GURUGRAM | E245: Vikram | F245: P105 | G245: Marketplace | H245: Corporate | I245: 1 | J245: 0.1 | K245: upi | L245: No | M245: 3
A246: ORD-5245 | B246: 45886 | C246: 45893 | D246: Faridabad | E246: Sana | F246: P108 | G246: Marketplace | H246: Corporate | I246: 3 | J246: 0 | K246: upi | L246: No | M246: 3
A247: ORD-5246 | B247: 45857 | C247: 45860 | D247: New Delhi | E247: Arjun | F247: P105 | G247: Corporate | H247: Corporate | I247: 3 | J247: 0 | K247: upi | L247: No | M247: 3
A248: ORD-5247 | B248: 46014 | C248: 46021 | D248: noida | E248: Ananya | F248: P104 | G248: Retail Store | H248: Corporate | I248: 3 | J248: 0.1 | K248: Net Banking | L248: No | M248: 4
A249: ORD-5248 | B249: 45760 | C249: 45763 | D249: MATHURA | E249: Rohan | F249: P104 | G249: Marketplace | H249: Consumer | I249: 5 | J249: 0.2 | K249: upi | L249: No | M249: 5
A250: ORD-5249 | B250: 45714 | C250: 45720 | D250: Gurgaon | E250: Meera | F250: P106 | G250: Retail Store | H250: Consumer | I250: 1 | J250: 0.15 | K250: UPI | L250: No | M250: 4
A251: ORD-5250 | B251: 45776 | C251: 45778 | D251: faridabad | E251: Vikram | F251: P109 | G251: Corporate | H251: Consumer | I251: 5 | J251: 0 | K251: Net Banking | L251: No | M251: 5
A252: ORD-5251 | B252: 45788 | C252: 45791 | D252: delhi | E252: Sana | F252: P106 | G252: Retail Store | H252: Consumer | I252: 1 | J252: 0 | K252: Net Banking | L252: No | M252: 3
A253: ORD-5252 | B253: 45995 | C253: 46003 | D253: noida | E253: Arjun | F253: P107 | G253: Marketplace | H253: Corporate | I253: 2 | J253: 0 | K253: Debit Card | L253: No | M253: 4
A254: ORD-5253 | B254: 45878 | C254: 45884 | D254: MATHURA | E254: Ananya | F254: P110 | G254: Website | H254: Small Business | I254: 2 | J254: 0.05 | K254: Cash on Delivery | L254: No | M254: 3
A255: ORD-5254 | B255: 45730 | C255: 45732 | D255: Gurugram | E255: Rohan | F255: P104 | G255: Website | H255: Consumer | I255: 3 | J255: 0.15 | K255: UPI | L255: No | M255: 5
... A299: ORD-5298 | B299: 45952 | C299: 45957 | D299: mathura | E299: Vikram | F299: P109 | G299: Retail Store | H299: Consumer | I299: 3 | J299: 0 | K299: COD | L299: No | M299: 4
A300: ORD-5299 | B300: 45979 | C300: 45987 | E300: Sana | F300: P109 | G300: Marketplace | H300: Consumer | I300: 5 | J300: 0.1 | K300: upi | L300: No | M300: 4
A301: ORD-5300 | B301: 45949 | C301: 45955 | D301: FARIDABAD | E301: Arjun | F301: P102 | G301: Website | H301: Consumer | I301: 1 | J301: 0.2 | K301: UPI | L301: No | M301: 4
A302: ORD-5301 | B302: 45724 | C302: 45725 | D302: Delhi | E302: Ananya | F302: P104 | G302: Corporate | H302: Small Business | I302: 2 | J302: 0 | K302: credit card | L302: No | M302: 4
A303: ORD-5302 | B303: 45665 | C303: 45666 | D303: Noida | E303: Rohan | F303: P112 | G303: Website | H303: Small Business | I303: 4 | J303: 0 | K303: credit card | L303: No | M303: 4
A304: ORD-5303 | B304: 45899 | C304: 45901 | D304: Mathura | E304: Meera | F304: P108 | G304: Retail Store | H304: Small Business | I304: 2 | J304: 0 | K304: credit card | L304: No | M304: 4
A305: ORD-5304 | B305: 45771 | C305: 45773 | D305: Gurugram | E305: Vikram | F305: P106 | G305: Retail Store | H305: Corporate | I305: 4 | J305: 0.15 | K305: Net Banking | L305: No | M305: 5
A306: ORD-5305 | B306: 45820 | C306: 45827 | D306: FARIDABAD | E306: Sana | F306: P103 | G306: Corporate | H306: Corporate | I306: 2 | J306: 0.2 | K306: Credit Card | L306: No | M306: 5
A307: ORD-5306 | B307: 45864 | C307: 45866 | D307: DELHI | E307: Arjun | F307: P105 | G307: Corporate | H307: Corporate | I307: 1 | J307: 0 | K307: COD | L307: No | M307: 5
A308: ORD-5307 | B308: 45882 | C308: 45883 | D308: NOIDA | E308: Ananya | F308: P104 | G308: Corporate | H308: Small Business | I308: 4 | J308: 0 | K308: Credit Card | L308: No | M308: 4
A309: ORD-5308 | B309: 45861 | C309: 45867 | D309: MATHURA | E309: Rohan | F309: P111 | G309: Website | H309: Consumer | I309: 5 | J309: 0.2 | K309: COD | L309: Yes | M309: 1
A310: ORD-5309 | B310: 45841 | C310: 45843 | D310: Gurugram | E310: Meera | F310: P106 | G310: Website | H310: Corporate | I310: 1 | J310: 0.05 | K310: Credit Card | L310: No | M310: 4
A311: ORD-5310 | B311: 45891 | C311: 45899 | D311: Faridabad | E311: Vikram | F311: P110 | G311: Marketplace | H311: Consumer | I311: 4 | J311: 0.1 | K311: Credit Card | L311: No | M311: 5
A312: ORD-5311 | B312: 45806 | C312: 45807 | D312: Delhi | E312: Sana | F312: P104 | G312: Marketplace | H312: Small Business | I312: 4 | J312: 0.15 | K312: Credit Card | L312: No | M312: 5
... A328: ORD-5327 | B328: 45969 | C328: 45977 | D328: Noida | E328: Meera | F328: P107 | G328: Website | H328: Small Business | I328: 3 | J328: 0.1 | K328: Net Banking | L328: No | M328: 3
A329: ORD-5328 | B329: 45964 | C329: 45971 | E329: Vikram | F329: P101 | G329: Website | H329: Corporate | I329: 2 | J329: 0.1 | K329: Debit Card | L329: No | M329: 3
A330: ORD-5329 | B330: 45783 | C330: 45784 | D330: GURUGRAM | E330: Sana | F330: P108 | G330: Website | H330: Small Business | I330: 5 | J330: 0.1 | K330: credit card | L330: No | M330: 4
...

Sheet Pivot_Analysis
A1: Row Labels | B1: Sum of Net_Revenue | C1: Sum of Profit | E1: Row Labels | F1: Sum of Net_Revenue | G1: Sum of Profit | I1: Row Labels | J1: Sum of Net_Revenue | K1: Sum of Profit | M1: Row Labels | N1: Sum of Net_Revenue | O1: Sum of Profit | Q1: Row Labels | R1: Sum of Net_Revenue | S1: Sum of Profit
A2: 45658 | B2: 347480.45 | C2: 102260.45 | E2: Delhi | F2: 833653.8 | G2: 237983.8 | I2: Accessories | J2: 835809.05 | K2: 328119.05 | M2: Corporate | N2: 1020686.2 | O2: 297116.25 | Q2: Ananya | R2: 743898.05 | S2: 194048.05
A3: 45689 | B3: 227343.75 | C3: 67583.75 | E3: Faridabad | F3: 1028136.2 | G3: 282666.25 | I3: Audio | J3: 441031.9 | K3: 153181.9 | M3: Marketplace | N3: 952633.3 | O3: 256143.3 | Q3: Arjun | R3: 623600.85 | S3: 171100.85
A4: 45717 | B4: 398596 | C4: 105396 | E4: Gurugram | F4: 706352.1 | G4: 197342.1 | I4: Displays | J4: 879382.35 | K4: 196882.35 | M4: Retail Store | N4: 1009244.5 | O4: 297964.5 | Q4: Meera | R4: 713308.7 | S4: 193018.7
A5: 45748 | B5: 397527.6 | C5: 106417.6 | E5: Mathura | F5: 674139.95 | G5: 190179.95 | I5: Furniture | J5: 1050341.9 | K5: 269241.95 | M5: Website | N5: 1199698.2 | O5: 318998.2 | Q5: Rohan | R5: 707121.85 | S5: 215411.85
A6: 45778 | B6: 366911.05 | C6: 118641.05 | E6: Noida | F6: 799625.05 | G6: 228725.05 | I6: Storage | J6: 975697 | K6: 222797 | M6: Grand Total | N6: 4182262.2 | O6: 1170222.2 | Q6: Sana | R6: 765844.6 | S6: 206614.6
A7: 45809 | B7: 318411.2 | C7: 94751.2 | E7: Unknown | F7: 140355.1 | G7: 33325.1 | I7: Grand Total | J7: 4182262.2 | K7: 1170222.2 | Q7: Vikram | R7: 628488.2 | S7: 190028.2
A8: 45839 | B8: 273176.4 | C8: 74026.4 | E8: Grand Total | F8: 4182262.2 | G8: 1170222.3 | Q8: Grand Total | R8: 4182262.2 | S8: 1170222.2
A9: 45870 | B9: 426069.2 | C9: 104249.2
A10: 45901 | B10: 510108.75 | C10: 138588.75
A11: 45931 | B11: 320910.3 | C11: 83590.3
A12: 45962 | B12: 395578.5 | C12: 120018.5
A13: 45992 | B13: 200149.05 | C13: 54699.05
A14: Grand Total | B14: 4182262.2 | C14: 1170222.2

Sheet Sales_Targets
A1: Monthly Salesperson Targets | D1: Salesperson Vs Target
A3: Salesperson | B3: Monthly_Revenue_Target | C3: Monthly_Profit_Target | D3: Salesperson | E3: Actual Monthly Revenue | F3: Monthly Revenue Target
A4: Ananya | B4: 420000 | C4: 95000 | D4: =A4 -> Ananya | E4: =_xlfn.XLOOKUP(D4,Pivot_Analysis!$Q$2:$Q$7,Pivot_Analysis!$R$2:$R$7,0)/12 -> 61991.504 | F4: =_xlfn.XLOOKUP(D4,$A$4:$A$9,$B$4:$B$9,0) -> 420000
A5: Rohan | B5: 445000 | C5: 102000 | D5: =A5 -> Rohan | E5: =_xlfn.XLOOKUP(D5,Pivot_Analysis!$Q$2:$Q$7,Pivot_Analysis!$R$2:$R$7,0)/12 -> 58926.821 | F5: =_xlfn.XLOOKUP(D5,$A$4:$A$9,$B$4:$B$9,0) -> 445000
A6: Meera | B6: 470000 | C6: 109000 | D6: =A6 -> Meera | E6: =_xlfn.XLOOKUP(D6,Pivot_Analysis!$Q$2:$Q$7,Pivot_Analysis!$R$2:$R$7,0)/12 -> 59442.392 | F6: =_xlfn.XLOOKUP(D6,$A$4:$A$9,$B$4:$B$9,0) -> 470000
A7: Vikram | B7: 495000 | C7: 116000 | D7: =A7 -> Vikram | E7: =_xlfn.XLOOKUP(D7,Pivot_Analysis!$Q$2:$Q$7,Pivot_Analysis!$R$2:$R$7,0)/12 -> 52374.017 | F7: =_xlfn.XLOOKUP(D7,$A$4:$A$9,$B$4:$B$9,0) -> 495000
A8: Sana | B8: 520000 | C8: 123000 | D8: =A8 -> Sana | E8: =_xlfn.XLOOKUP(D8,Pivot_Analysis!$Q$2:$Q$7,Pivot_Analysis!$R$2:$R$7,0)/12 -> 63820.383 | F8: =_xlfn.XLOOKUP(D8,$A$4:$A$9,$B$4:$B$9,0) -> 520000
A9: Arjun | B9: 545000 | C9: 130000 | D9: =A9 -> Arjun | E9: =_xlfn.XLOOKUP(D9,Pivot_Analysis!$Q$2:$Q$7,Pivot_Analysis!$R$2:$R$7,0)/12 -> 51966.737 | F9: =_xlfn.XLOOKUP(D9,$A$4:$A$9,$B$4:$B$9,0) -> 545000

Sheet Dashboard_Canvas
A1: E-commerce Sales & Profitability Dashboard
A4: Net Revenue | D4: Profit | G4: Profit Margin | J4: Orders | M4: Return Rate
A5: =Pivot_Analysis!B14 -> 4182262.2 | D5: =Pivot_Analysis!C14 -> 1170222.2 | G5: =IFERROR(D5/A5,0) -> 0.27980604 | J5: =COUNTA(RawSalesTable5[Order_ID]) -> 360 | M5: =COUNTIF(RawSalesTable5[Returned],"Yes")/COUNTA(RawSalesTable5[Order_ID]) -> 0.069444444
A37: Three recommendations
A38: 1. Investigate order volume, discounts, returns and product mix in February and December, then plan targeted promotions or inventory adjustments.
A39: 2. Reset salesperson targets using historical monthly performance and introduce achievable staged milestones with coaching.
A40: 3. Replicate the product and channel practices driving Faridabad and Accessories while correcting Unknown city records before making geographic decisions.
A41: Findings
A42: 1. September generated the highest monthly net revenue (₹510,109) and profit (₹138,589).
A43: 2. December generated the lowest monthly profit (₹54,699), followed by February (₹67,584).
A44: 3. Accessories generated the highest category profit (₹328,119), while Furniture generated the highest category revenue (₹1,050,342).
A45: 4. Faridabad was the strongest city, producing ₹1,028,136 in net revenue and ₹282,666 in profit.
A46: 5. None of the six salespersons met the monthly revenue target; achievement ranged from 9.5% for Arjun to 14.8% for Ananya.

Sheet Product_Lookup
A1: Product Lookup — use this table for XLOOKUP
A3: Product_Code | B3: Product_Name | C3: Category | D3: Unit_Price | E3: Unit_Cost
A4: P101 | B4: Wireless Mouse | C4: Accessories | D4: 799 | E4: 420
A5: P102 | B5: Mechanical Keyboard | C5: Accessories | D5: 2499 | E5: 1450
A6: P103 | B6: HD Webcam | C6: Accessories | D6: 2899 | E6: 1700
A7: P104 | B7: USB-C Hub | C7: Accessories | D7: 1599 | E7: 870
A8: P105 | B8: 24-inch Monitor | C8: Displays | D8: 12999 | E8: 9100
A9: P106 | B9: Wireless Headset | C9: Audio | D9: 3499 | E9: 2100
A10: P107 | B10: Laptop Stand | C10: Accessories | D10: 1899 | E10: 980
A11: P108 | B11: SSD 1TB | C11: Storage | D11: 6999 | E11: 4900
A12: P109 | B12: Ergonomic Chair | C12: Furniture | D12: 10499 | E12: 7600
A13: P110 | B13: LED Desk Lamp | C13: Furniture | D13: 1999 | E13: 1050
A14: P111 | B14: Bluetooth Speaker | C14: Audio | D14: 2799 | E14: 1650
A15: P112 | B15: Portable HDD 2TB | C15: Storage | D15: 5899 | E15: 4100

Sheet Work_Log
A1: Project Work Log
A3: Date | B3: Task | C3: Done alone? | D3: Help used | E3: Decision/check | F3: What I learned
A4: 24/8/26 | B4: Data cleaning, lookups and calculated columns | C4: With guidance | D4: Excel documentation | E4: Validated calculations and data quality | F4: Learned how I can clean and analyze big data in very short amount of time and certain calculations and how xlookup is more useful than vlookup
A5: 25/8/26 | B5: PivotTables, KPIs, charts and insights | C5: With guidance | D5: Excel documentation | E5: Validated calculations and data quality | F5: Learned difference b/w kpi and pivot table and how different graphs affect understanding as a viewer
